{"lastRefresh":"2026-03-10T13:10:04.011Z","gerais":[{"nome":"CARRINHOCHEIO","desconto":"12%","valorMinimo":"Compra mínima R$ 79","limite":"Limite de R$ 60","tipo":"GERAL","dataExtracao":"2026-03-10T09:01:20.997-03:00","validWith":"ML_COOKIES","source":"telegram-so-cupons","dataAdicao":"2026-03-10T09:01:23.873-03:00"},{"nome":"MELIMAISPRAVC","desconto":"R$ 100","valorMinimo":"Compra mínima R$ 599","limite":"Limite de R$ 100","tipo":"GERAL","dataExtracao":"2026-03-10T09:20:48.822-03:00","exclusivoMeliPlus":true,"validWith":"ML_COOKIES","dataAdicao":"2026-03-10T09:22:06.588-03:00"}],"especificos":[{"nome":"GENTILLEITOR","desconto":"15%","valorMinimo":"Compra mínima R$ 19","limite":"Limite de R$ 30","tipo":"ESPECÍFICO","dataExtracao":"2026-03-03T13:38:36.305-03:00","link":"https://lista.mercadolivre.com.br/_Container_querido-e-gentil-leitor-fev26","validWith":"ML_COOKIES","linkOriginal":"https://lista.mercadolivre.com.br/_Container_querido-e-gentil-leitor-fev26","linkAfiliado":"https://meli.la/2ydxpMT","dataAdicao":"2026-03-03T13:39:54.214-03:00"},{"nome":"MDMD10","desconto":"10%","valorMinimo":"Compra mínima R$ 29","limite":"Limite de R$ 50","tipo":"ESPECÍFICO","dataExtracao":"2026-03-03T14:10:48.371-03:00","link":"https://lista.mercadolivre.com.br/_Container_AfiliadoMadeiraMadeira","validWith":"ML_COOKIES","source":"telegram-ml","linkOriginal":"https://lista.mercadolivre.com.br/_Container_AfiliadoMadeiraMadeira","linkAfiliado":"https://meli.la/1EEC5zw","dataAdicao":"2026-03-03T14:12:19.737-03:00"},{"nome":"CORREPROMELI","desconto":"20%","valorMinimo":"Compra mínima R$ 29","limite":"Limite de R$ 60","tipo":"ESPECÍFICO","dataExtracao":"2026-03-09T09:17:31.557-03:00","link":"https://lista.mercadolivre.com.br/_Container_mercado-aff","linkOriginal":"https://lista.mercadolivre.com.br/_Container_mercado-aff","linkAfiliado":"https://meli.la/2Lxtdkv","dataAdicao":"2026-03-09T09:18:10.286-03:00"},{"nome":"MELHOROFERTA","desconto":"20%","valorMinimo":"Compra mínima R$ 29","limite":"Limite de R$ 60","tipo":"ESPECÍFICO","dataExtracao":"2026-03-09T09:17:31.558-03:00","link":"https://lista.mercadolivre.com.br/_Container_especialidades-aff","linkOriginal":"https://lista.mercadolivre.com.br/_Container_especialidades-aff","linkAfiliado":"https://meli.la/2mRVfrc","dataAdicao":"2026-03-09T09:18:13.225-03:00"},{"nome":"SUPER20CUIDADOS","desconto":"20%","valorMinimo":"Compra mínima R$ 159","limite":"Limite de R$ 40","tipo":"ESPECÍFICO","dataExtracao":"2026-03-10T09:38:50.526-03:00","link":"https://lista.mercadolivre.com.br/_Container_cpg-afiliados-home-e-personal-care-cupom","linkOriginal":"https://lista.mercadolivre.com.br/_Container_cpg-afiliados-home-e-personal-care-cupom","linkAfiliado":"https://meli.la/1ZimPfj","dataAdicao":"2026-03-10T09:38:53.810-03:00"}]}